headcache/__init__.py
headcache/file_watcher.py
headcache/headcache.py
headcache/md_parser.py
headcache/preview_style.css
headcache/search.py
headcache/style.qss
headcache/ui_components.py
headcache-0.1.2.dist-info/DESCRIPTION.rst
headcache-0.1.2.dist-info/METADATA
headcache-0.1.2.dist-info/RECORD
headcache-0.1.2.dist-info/WHEEL
headcache-0.1.2.dist-info/entry_points.txt
headcache-0.1.2.dist-info/metadata.json
headcache-0.1.2.dist-info/top_level.txt
