Metadata-Version: 2.0
Name: headcache
Version: 0.1.2
Summary: note-typing program.
Home-page: https://github.com/s9w/headcache
Author: Sebastian Werhausen
Author-email: swerhausen@gmail.com
License: UNKNOWN
Platform: UNKNOWN
Requires-Dist: mistune
Requires-Dist: watchdog
Requires-Dist: whoosh
